README.md
ptbtok.py
setup.py
ptbtok.egg-info/PKG-INFO
ptbtok.egg-info/SOURCES.txt
ptbtok.egg-info/dependency_links.txt
ptbtok.egg-info/not-zip-safe
ptbtok.egg-info/top_level.txt